[
    {
        "podcastName": "flow",
        "episode": "CBUM - Flow #319",
        "videoId": "pQSuQmUfS30",
        "categortes": [
            "saúde",
            "esporte",
            "bodybuilder"
        ]
    },
    {
        "podcastName": "flow",
        "episode": "RUBENS BARRICHELLO - Flow #339",
        "videoId": "4KDGTdioV4I",
        "categories": [
            "esporte",
            "corrida"
        ]
    },
    {
        "podcastName": "teste",
        "episode": "Tetse - teste 888339",
        "videoId": "0000",
        "categories": [
            "esporte",
            "corrida",
            "Programação"
        ]
    }
]